Estudo Dirigido/ED09/verilog/clock.v
// Matheus de Almeida Moreira
// 848813

// clock.v - Gerador de clock

module clock (output reg clk);
    initial begin
        clk = 1'b0;
    end

    always begin
        #12 clk = ~clk;  // Clock alterna a cada 12 unidades de tempo
    end
endmodule

Estudo Dirigido/ED09/verilog/Guia_0905.v
// ---------------------------
// Guia_0905.v
// Gerador de pulso com marcação de 3 unidades, sincronizado no clock
// ---------------------------

// incluir o clock
`include "clock.v"

// ---------------------------
// -- pulse generator
// ---------------------------
module pulse ( output reg signal, input clock );

initial begin
    signal = 1'b0;
end

always @(posedge clock) begin
    signal = 1'b1;
    #3 signal = 1'b0; // Condição para desligar: 3 unidades de tempo
end

endmodule


module Guia_0905;
wire clk;
wire pulse_out;

clock CLK1 ( clk );
pulse PULSE1 ( pulse_out, clk );

initial begin
    $dumpfile("Guia_0905.vcd");
    $dumpvars(1, clk, pulse_out);
    #200 $finish;
end

endmodule

Estudo Dirigido/ED09/vcd/Guia_0905.vcd
$date
	Sat Apr 26 15:48:08 2025
$end
$version
	Icarus Verilog
$end
$timescale
	1s
$end
$scope module Guia_0905 $end
$var wire 1 ! clk $end
$upscope $end
$scope module Guia_0905 $end
$var wire 1 " pulse_out $end
$upscope $end
$enddefinitions $end
$comment Show the parameter values. $end
$dumpall
$end
#0
$dumpvars
0"
0!
$end
#12
1"
1!
#15
0"
#24
0!
#36
1"
1!
#39
0"
#48
0!
#60
1"
1!
#63
0"
#72
0!
#84
1"
1!
#87
0"
#96
0!
#108
1"
1!
#111
0"
#120
0!
#132
1"
1!
#135
0"
#144
0!
#156
1"
1!
#159
0"
#168
0!
#180
1"
1!
#183
0"
